topsis/102017067.py
102017067_topsis-1.0.0.dist-info/METADATA
102017067_topsis-1.0.0.dist-info/WHEEL
102017067_topsis-1.0.0.dist-info/entry_points.txt
102017067_topsis-1.0.0.dist-info/top_level.txt
102017067_topsis-1.0.0.dist-info/RECORD
